{
  "version": "1.0",
  "entity_type": "character",
  "direction": "R",
  "direction_name": "오른쪽",
  "motion": "walk",
  "motion_name": "이동",
  "frame": 0,
  "total_frames": 6,
  "fps": 10,
  "loop": true,
  "canvas": {
    "width": 64,
    "height": 64
  },
  "mirrored_from": "L",
  "keypoints": {
    "format": "openpose_18",
    "points": [
      [
        34.0,
        10,
        1.0
      ],
      [
        32.0,
        16,
        1.0
      ],
      [
        35.0,
        18,
        1.0
      ],
      [
        40.0,
        28.0,
        1.0
      ],
      [
        42.0,
        36,
        1.0
      ],
      [
        29.0,
        18,
        1.0
      ],
      [
        27.0,
        28.0,
        0.5
      ],
      [
        29.0,
        36,
        0.3
      ],
      [
        34.0,
        36,
        1.0
      ],
      [
        34.0,
        46.0,
        1.0
      ],
      [
        34.0,
        56.0,
        1.0
      ],
      [
        30.0,
        36,
        0.5
      ],
      [
        30.0,
        46.0,
        0.5
      ],
      [
        30.0,
        56.0,
        0.5
      ],
      [
        33.0,
        8,
        1.0
      ],
      [
        36.0,
        8,
        0.0
      ],
      [
        37.0,
        9,
        1.0
      ],
      [
        28.0,
        9,
        0.0
      ]
    ],
    "names": [
      "nose",
      "neck",
      "right_shoulder",
      "right_elbow",
      "right_wrist",
      "left_shoulder",
      "left_elbow",
      "left_wrist",
      "right_hip",
      "right_knee",
      "right_ankle",
      "left_hip",
      "left_knee",
      "left_ankle",
      "right_eye",
      "left_eye",
      "right_ear",
      "left_ear"
    ]
  }
}