{
  "atlas": "atlas_vfx_void_wanderer",
  "size": {
    "w": 4096,
    "h": 512
  },
  "sprites": [
    {
      "file": "VFX-VOI-001.png",
      "x": 0,
      "y": 0,
      "w": 512,
      "h": 64
    },
    {
      "file": "VFX-VOI-002.png",
      "x": 514,
      "y": 0,
      "w": 512,
      "h": 64
    },
    {
      "file": "VFX-VOI-003.png",
      "x": 1028,
      "y": 0,
      "w": 512,
      "h": 64
    },
    {
      "file": "VFX-VOI-004.png",
      "x": 1542,
      "y": 0,
      "w": 512,
      "h": 64
    },
    {
      "file": "VFX-VOI-005.png",
      "x": 2056,
      "y": 0,
      "w": 512,
      "h": 64
    },
    {
      "file": "VFX-VOI-006.png",
      "x": 2570,
      "y": 0,
      "w": 512,
      "h": 64
    },
    {
      "file": "VFX-VOI-007.png",
      "x": 3084,
      "y": 0,
      "w": 512,
      "h": 64
    },
    {
      "file": "VFX-VOI-008.png",
      "x": 0,
      "y": 66,
      "w": 512,
      "h": 64
    },
    {
      "file": "VFX-VOI-009.png",
      "x": 514,
      "y": 66,
      "w": 512,
      "h": 64
    },
    {
      "file": "VFX-VOI-010.png",
      "x": 1028,
      "y": 66,
      "w": 512,
      "h": 64
    },
    {
      "file": "VFX-VOI-011.png",
      "x": 1542,
      "y": 66,
      "w": 512,
      "h": 64
    },
    {
      "file": "VFX-VOI-012.png",
      "x": 2056,
      "y": 66,
      "w": 512,
      "h": 64
    },
    {
      "file": "VFX-VOI-013.png",
      "x": 2570,
      "y": 66,
      "w": 512,
      "h": 64
    },
    {
      "file": "VFX-VOI-014.png",
      "x": 3084,
      "y": 66,
      "w": 512,
      "h": 64
    },
    {
      "file": "VFX-VOI-015.png",
      "x": 0,
      "y": 132,
      "w": 512,
      "h": 64
    },
    {
      "file": "VFX-VOI-016.png",
      "x": 514,
      "y": 132,
      "w": 512,
      "h": 64
    },
    {
      "file": "VFX-VOI-017.png",
      "x": 1028,
      "y": 132,
      "w": 512,
      "h": 64
    },
    {
      "file": "VFX-VOI-018.png",
      "x": 1542,
      "y": 132,
      "w": 512,
      "h": 64
    },
    {
      "file": "VFX-VOI-019.png",
      "x": 2056,
      "y": 132,
      "w": 512,
      "h": 64
    },
    {
      "file": "VFX-VOI-020.png",
      "x": 2570,
      "y": 132,
      "w": 512,
      "h": 64
    },
    {
      "file": "VFX-VOI-021.png",
      "x": 3084,
      "y": 132,
      "w": 512,
      "h": 64
    },
    {
      "file": "VFX-VOI-022.png",
      "x": 0,
      "y": 198,
      "w": 512,
      "h": 64
    },
    {
      "file": "VFX-VOI-023.png",
      "x": 514,
      "y": 198,
      "w": 512,
      "h": 64
    },
    {
      "file": "VFX-VOI-024.png",
      "x": 1028,
      "y": 198,
      "w": 512,
      "h": 64
    },
    {
      "file": "VFX-VOI-025.png",
      "x": 1542,
      "y": 198,
      "w": 512,
      "h": 64
    },
    {
      "file": "VFX-VOI-026.png",
      "x": 2056,
      "y": 198,
      "w": 512,
      "h": 64
    },
    {
      "file": "VFX-VOI-027.png",
      "x": 2570,
      "y": 198,
      "w": 512,
      "h": 64
    },
    {
      "file": "VFX-VOI-028.png",
      "x": 3084,
      "y": 198,
      "w": 512,
      "h": 64
    },
    {
      "file": "VFX-VOI-029.png",
      "x": 0,
      "y": 264,
      "w": 512,
      "h": 64
    },
    {
      "file": "VFX-VOI-030.png",
      "x": 514,
      "y": 264,
      "w": 512,
      "h": 64
    }
  ],
  "count": 30
}